tuya_device_handlers/__init__.py
tuya_device_handlers/builder/__init__.py
tuya_device_handlers/builder/base_quirk.py
tuya_device_handlers/const.py
tuya_device_handlers/device_wrapper/__init__.py
tuya_device_handlers/device_wrapper/base.py
tuya_device_handlers/device_wrapper/binary_sensor.py
tuya_device_handlers/device_wrapper/common.py
tuya_device_handlers/device_wrapper/const.py
tuya_device_handlers/device_wrapper/exception.py
tuya_device_handlers/device_wrapper/sensor.py
tuya_device_handlers/devices/__init__.py
tuya_device_handlers/helpers/__init__.py
tuya_device_handlers/helpers/homeassistant.py
tuya_device_handlers/helpers/utils.py
tuya_device_handlers/py.typed
tuya_device_handlers/raw_data_model.py
tuya_device_handlers/registry.py
tuya_device_handlers/type_information.py
tuya_device_handlers/utils.py
tuya_device_handlers-0.0.9.dist-info/METADATA
tuya_device_handlers-0.0.9.dist-info/WHEEL
tuya_device_handlers-0.0.9.dist-info/entry_points.txt
tuya_device_handlers-0.0.9.dist-info/licenses/LICENSE.rst
tuya_device_handlers-0.0.9.dist-info/RECORD
