Metadata-Version: 2.4
Name: tuya-device-handlers
Version: 0.0.9
Summary: Tuya quirks library
License: MIT
License-File: LICENSE.rst
Keywords: tuya
Author: epenet
Requires-Python: >=3.12,<4.0
Classifier: Intended Audience :: Developers
Classifier: Intended Audience :: System Administrators
Classifier: License :: OSI Approved :: MIT License
Classifier: Operating System :: OS Independent
Classifier: Programming Language :: Python :: 3
Classifier: Programming Language :: Python :: 3.12
Classifier: Programming Language :: Python :: 3.13
Classifier: Programming Language :: Python :: 3.14
Classifier: Topic :: Home Automation
Provides-Extra: cli
Requires-Dist: click (>=8.0.1) ; extra == "cli"
Requires-Dist: tuya-device-sharing-sdk (>=0.2.4)
Project-URL: Changelog, https://github.com/hacf-fr/tuya-device-handlers/releases
Project-URL: Documentation, https://tuya-device-handlers.readthedocs.io
Project-URL: Homepage, https://github.com/hacf-fr/tuya-device-handlers
Project-URL: Repository, https://github.com/hacf-fr/tuya-device-handlers
